scrapy_save_to_qiniu/__init__.py
scrapy_save_to_qiniu/pipelines.py
scrapy_save_to_qiniu-0.2.0.dist-info/METADATA
scrapy_save_to_qiniu-0.2.0.dist-info/WHEEL
scrapy_save_to_qiniu-0.2.0.dist-info/top_level.txt
scrapy_save_to_qiniu-0.2.0.dist-info/RECORD
